Lab2/problem2_traffic/traffic_ligth.v
// Moore FSM for a two-road (NS/EW) traffic light controller.
module traffic_light (
    input  wire clk,
    input  wire rst,          // Synchronous, active-high reset
    input  wire tick,         // 1 Hz tick input
    output reg  ns_g, ns_y, ns_r, // North-South 
    output reg  ew_g, ew_y, ew_r  // East-West 
);

    // State encoding
    parameter NS_GREEN  = 2'b00;
    parameter NS_YELLOW = 2'b01;
    parameter EW_GREEN  = 2'b10;
    parameter EW_YELLOW = 2'b11;

    // State regisers
    reg [1:0] current_state, next_state;

    // Counter tick 
    reg [2:0] tick_counter; // 000(1tick) 001 010 011 100(5ticks)
    // State Register
    always @(posedge clk) begin
        if (rst) begin
            current_state <= NS_GREEN;
        end else begin
            current_state <= next_state;
        end
    end

    // Next State Logic and Counter Block (Combinational)
    always @(*) begin
        next_state = current_state; // Default staysame state
        case (current_state)
            NS_GREEN: begin
                if (tick && (tick_counter == 3'd4)) begin
                    next_state = NS_YELLOW;
                end
            end
            NS_YELLOW: begin
                if (tick && (tick_counter == 3'd1)) begin
                    next_state = EW_GREEN;
                end
            end
            EW_GREEN: begin
                if (tick && (tick_counter == 3'd4)) begin
                    next_state = EW_YELLOW;
                end
            end
            EW_YELLOW: begin
                if (tick && (tick_counter == 3'd1)) begin
                    next_state = NS_GREEN;
                end
            end
            default: next_state = NS_GREEN;
        endcase
    end
    
    // Tick Counter Logic (Sequential)
    always @(posedge clk) begin
        if (rst) begin
            tick_counter <= 3'd0;
        // If state is about to change on the next clock, reset counter
        end else if (next_state != current_state) begin
            tick_counter <= 3'd0;
        // Otherwise, increment on each tick
        end else if (tick) begin
            tick_counter <= tick_counter + 1;
        end
    end

    // Output 
    always @(*) begin
        // Default all lights to off
        {ns_g, ns_y, ns_r} = 3'b001; // Default to RED
        {ew_g, ew_y, ew_r} = 3'b001; // Default to RED
        
        case (current_state)
            NS_GREEN: begin
                ns_g = 1'b1; ns_r = 1'b0;
                ew_r = 1'b1;
            end
            NS_YELLOW: begin
                ns_y = 1'b1; ns_r = 1'b0;
                ew_r = 1'b1;
            end
            EW_GREEN: begin
                ew_g = 1'b1; ew_r = 1'b0;
                ns_r = 1'b1;
            end
            EW_YELLOW: begin
                ew_y = 1'b1; ew_r = 1'b0;
                ns_r = 1'b1;
            end
        endcase
    end

endmodule

Lab2/problem2_traffic/tb_traffic_light.v
// Testbench for the traffic_light module
`timescale 1ns / 1ps

module tb_traffic_light;

    // Inputs
    reg clk;
    reg rst;
    reg tick;

    // Outputs
    wire ns_g, ns_y, ns_r;
    wire ew_g, ew_y, ew_r;

    // Instantiate the Unit Under Test (UUT)
    traffic_light uut (
        .clk(clk), 
        .rst(rst), 
        .tick(tick), 
        .ns_g(ns_g), .ns_y(ns_y), .ns_r(ns_r),
        .ew_g(ew_g), .ew_y(ew_y), .ew_r(ew_r)
    );

    // Clock generation (50 MHz equivalent period)
    initial begin
        clk = 0;
        forever #10 clk = ~clk; // 20ns period
    end

    // Test sequence
    initial begin
        // Dump waves
        $dumpfile("waveform.vcd");
        $dumpvars(0, tb_traffic_light);

        // 1. Initialize and apply reset
        rst = 1;
        tick = 0;
        #50; // Wait a few clock cycles
        
        // 2. De-assert reset and start simulation
        rst = 0;
        #20;
        
        // 3. Generate 1 Hz tick (here simulated every 10 clock cycles for visibility)
        repeat (30) begin
            #190; // Wait for 9 clock cycles
            tick = 1; // Pulse tick for one clock cycle
            #20;
            tick = 0;
        end

        // 4. End simulation
        #100;
        $finish;
    end

endmodule

Lab2/problem2_traffic/waveform.vcd
$date
	Wed Sep 03 14:40:32 2025
$end
$version
	Icarus Verilog
$end
$timescale
	1ns
$end
$scope module tb_traffic_light $end
$var wire 1 ! ew_g $end
$var wire 1 " ew_r $end
$var wire 1 # ew_y $end
$var wire 1 $ ns_g $end
$var wire 1 % ns_r $end
$var wire 1 & ns_y $end
$var reg 1 ' clk $end
$var reg 1 ( rst $end
$var reg 1 ) tick $end
$scope module uut $end
$var wire 1 * clk $end
$var wire 1 + rst $end
$var wire 1 , tick $end
$var reg 2 - current_state [1:0] $end
$var reg 1 . ew_g $end
$var reg 1 / ew_r $end
$var reg 1 0 ew_y $end
$var reg 2 1 next_state [1:0] $end
$var reg 1 2 ns_g $end
$var reg 1 3 ns_r $end
$var reg 1 4 ns_y $end
$var reg 3 5 tick_counter [2:0] $end
$upscope $end
$upscope $end
$enddefinitions $end
#0
$dumpvars
bx 5
x4
x3
x2
b0 1
x0
x/
x.
bx -
0,
1+
0*
0)
1(
0'
x&
x%
x$
x#
x"
x!
$end
#10
0.
0!
00
0#
1/
1"
12
1$
04
0&
03
0%
b0 -
b0 5
1'
1*
#20
0'
0*
#30
1'
1*
#40
0'
0*
#50
1'
1*
0(
0+
#60
0'
0*
#70
1'
1*
#80
0'
0*
#90
1'
1*
#100
0'
0*
#110
1'
1*
#120
0'
0*
#130
1'
1*
#140
0'
0*
#150
1'
1*
#160
0'
0*
#170
1'
1*
#180
0'
0*
#190
1'
1*
#200
0'
0*
#210
1'
1*
#220
0'
0*
#230
1'
1*
#240
0'
0*
#250
1'
1*
#260
0'
0*
1)
1,
#270
b1 5
1'
1*
#280
0'
0*
0)
0,
#290
1'
1*
#300
0'
0*
#310
1'
1*
#320
0'
0*
#330
1'
1*
#340
0'
0*
#350
1'
1*
#360
0'
0*
#370
1'
1*
#380
0'
0*
#390
1'
1*
#400
0'
0*
#410
1'
1*
#420
0'
0*
#430
1'
1*
#440
0'
0*
#450
1'
1*
#460
0'
0*
#470
b10 5
1'
1*
1)
1,
#480
0'
0*
#490
1'
1*
0)
0,
#500
0'
0*
#510
1'
1*
#520
0'
0*
#530
1'
1*
#540
0'
0*
#550
1'
1*
#560
0'
0*
#570
1'
1*
#580
0'
0*
#590
1'
1*
#600
0'
0*
#610
1'
1*
#620
0'
0*
#630
1'
1*
#640
0'
0*
#650
1'
1*
#660
0'
0*
#670
1'
1*
#680
0'
0*
1)
1,
#690
b11 5
1'
1*
#700
0'
0*
0)
0,
#710
1'
1*
#720
0'
0*
#730
1'
1*
#740
0'
0*
#750
1'
1*
#760
0'
0*
#770
1'
1*
#780
0'
0*
#790
1'
1*
#800
0'
0*
#810
1'
1*
#820
0'
0*
#830
1'
1*
#840
0'
0*
#850
1'
1*
#860
0'
0*
#870
1'
1*
#880
0'
0*
#890
b1 1
b100 5
1'
1*
1)
1,
#900
0'
0*
#910
b0 1
1'
1*
0)
0,
#920
0'
0*
#930
1'
1*
#940
0'
0*
#950
1'
1*
#960
0'
0*
#970
1'
1*
#980
0'
0*
#990
1'
1*
#1000
0'
0*
#1010
1'
1*
#1020
0'
0*
#1030
1'
1*
#1040
0'
0*
#1050
1'
1*
#1060
0'
0*
#1070
1'
1*
#1080
0'
0*
#1090
1'
1*
#1100
b1 1
0'
0*
1)
1,
#1110
14
1&
02
0$
03
0%
b0 5
b1 -
1'
1*
#1120
0'
0*
0)
0,
#1130
1'
1*
#1140
0'
0*
#1150
1'
1*
#1160
0'
0*
#1170
1'
1*
#1180
0'
0*
#1190
1'
1*
#1200
0'
0*
#1210
1'
1*
#1220
0'
0*
#1230
1'
1*
#1240
0'
0*
#1250
1'
1*
#1260
0'
0*
#1270
1'
1*
#1280
0'
0*
#1290
1'
1*
#1300
0'
0*
#1310
b10 1
b1 5
1'
1*
1)
1,
#1320
0'
0*
#1330
b1 1
1'
1*
0)
0,
#1340
0'
0*
#1350
1'
1*
#1360
0'
0*
#1370
1'
1*
#1380
0'
0*
#1390
1'
1*
#1400
0'
0*
#1410
1'
1*
#1420
0'
0*
#1430
1'
1*
#1440
0'
0*
#1450
1'
1*
#1460
0'
0*
#1470
1'
1*
#1480
0'
0*
#1490
1'
1*
#1500
0'
0*
#1510
1'
1*
#1520
b10 1
0'
0*
1)
1,
#1530
0/
0"
1.
1!
04
0&
13
1%
b10 -
b0 5
1'
1*
#1540
0'
0*
0)
0,
#1550
1'
1*
#1560
0'
0*
#1570
1'
1*
#1580
0'
0*
#1590
1'
1*
#1600
0'
0*
#1610
1'
1*
#1620
0'
0*
#1630
1'
1*
#1640
0'
0*
#1650
1'
1*
#1660
0'
0*
#1670
1'
1*
#1680
0'
0*
#1690
1'
1*
#1700
0'
0*
#1710
1'
1*
#1720
0'
0*
#1730
b1 5
1'
1*
1)
1,
#1740
0'
0*
#1750
1'
1*
0)
0,
#1760
0'
0*
#1770
1'
1*
#1780
0'
0*
#1790
1'
1*
#1800
0'
0*
#1810
1'
1*
#1820
0'
0*
#1830
1'
1*
#1840
0'
0*
#1850
1'
1*
#1860
0'
0*
#1870
1'
1*
#1880
0'
0*
#1890
1'
1*
#1900
0'
0*
#1910
1'
1*
#1920
0'
0*
#1930
1'
1*
#1940
0'
0*
1)
1,
#1950
b10 5
1'
1*
#1960
0'
0*
0)
0,
#1970
1'
1*
#1980
0'
0*
#1990
1'
1*
#2000
0'
0*
#2010
1'
1*
#2020
0'
0*
#2030
1'
1*
#2040
0'
0*
#2050
1'
1*
#2060
0'
0*
#2070
1'
1*
#2080
0'
0*
#2090
1'
1*
#2100
0'
0*
#2110
1'
1*
#2120
0'
0*
#2130
1'
1*
#2140
0'
0*
#2150
b11 5
1'
1*
1)
1,
#2160
0'
0*
#2170
1'
1*
0)
0,
#2180
0'
0*
#2190
1'
1*
#2200
0'
0*
#2210
1'
1*
#2220
0'
0*
#2230
1'
1*
#2240
0'
0*
#2250
1'
1*
#2260
0'
0*
#2270
1'
1*
#2280
0'
0*
#2290
1'
1*
#2300
0'
0*
#2310
1'
1*
#2320
0'
0*
#2330
1'
1*
#2340
0'
0*
#2350
1'
1*
#2360
0'
0*
1)
1,
#2370
b11 1
b100 5
1'
1*
#2380
b10 1
0'
0*
0)
0,
#2390
1'
1*
#2400
0'
0*
#2410
1'
1*
#2420
0'
0*
#2430
1'
1*
#2440
0'
0*
#2450
1'
1*
#2460
0'
0*
#2470
1'
1*
#2480
0'
0*
#2490
1'
1*
#2500
0'
0*
#2510
1'
1*
#2520
0'
0*
#2530
1'
1*
#2540
0'
0*
#2550
1'
1*
#2560
0'
0*
#2570
10
1#
0.
0!
0/
0"
b11 -
b0 5
b11 1
1'
1*
1)
1,
#2580
0'
0*
#2590
1'
1*
0)
0,
#2600
0'
0*
#2610
1'
1*
#2620
0'
0*
#2630
1'
1*
#2640
0'
0*
#2650
1'
1*
#2660
0'
0*
#2670
1'
1*
#2680
0'
0*
#2690
1'
1*
#2700
0'
0*
#2710
1'
1*
#2720
0'
0*
#2730
1'
1*
#2740
0'
0*
#2750
1'
1*
#2760
0'
0*
#2770
1'
1*
#2780
0'
0*
1)
1,
#2790
b0 1
b1 5
1'
1*
#2800
b11 1
0'
0*
0)
0,
#2810
1'
1*
#2820
0'
0*
#2830
1'
1*
#2840
0'
0*
#2850
1'
1*
#2860
0'
0*
#2870
1'
1*
#2880
0'
0*
#2890
1'
1*
#2900
0'
0*
#2910
1'
1*
#2920
0'
0*
#2930
1'
1*
#2940
0'
0*
#2950
1'
1*
#2960
0'
0*
#2970
1'
1*
#2980
0'
0*
#2990
03
0%
12
1$
00
0#
1/
1"
b0 5
b0 -
b0 1
1'
1*
1)
1,
#3000
0'
0*
#3010
1'
1*
0)
0,
#3020
0'
0*
#3030
1'
1*
#3040
0'
0*
#3050
1'
1*
#3060
0'
0*
#3070
1'
1*
#3080
0'
0*
#3090
1'
1*
#3100
0'
0*
#3110
1'
1*
#3120
0'
0*
#3130
1'
1*
#3140
0'
0*
#3150
1'
1*
#3160
0'
0*
#3170
1'
1*
#3180
0'
0*
#3190
1'
1*
#3200
0'
0*
1)
1,
#3210
b1 5
1'
1*
#3220
0'
0*
0)
0,
#3230
1'
1*
#3240
0'
0*
#3250
1'
1*
#3260
0'
0*
#3270
1'
1*
#3280
0'
0*
#3290
1'
1*
#3300
0'
0*
#3310
1'
1*
#3320
0'
0*
#3330
1'
1*
#3340
0'
0*
#3350
1'
1*
#3360
0'
0*
#3370
1'
1*
#3380
0'
0*
#3390
1'
1*
#3400
0'
0*
#3410
b10 5
1'
1*
1)
1,
#3420
0'
0*
#3430
1'
1*
0)
0,
#3440
0'
0*
#3450
1'
1*
#3460
0'
0*
#3470
1'
1*
#3480
0'
0*
#3490
1'
1*
#3500
0'
0*
#3510
1'
1*
#3520
0'
0*
#3530
1'
1*
#3540
0'
0*
#3550
1'
1*
#3560
0'
0*
#3570
1'
1*
#3580
0'
0*
#3590
1'
1*
#3600
0'
0*
#3610
1'
1*
#3620
0'
0*
1)
1,
#3630
b11 5
1'
1*
#3640
0'
0*
0)
0,
#3650
1'
1*
#3660
0'
0*
#3670
1'
1*
#3680
0'
0*
#3690
1'
1*
#3700
0'
0*
#3710
1'
1*
#3720
0'
0*
#3730
1'
1*
#3740
0'
0*
#3750
1'
1*
#3760
0'
0*
#3770
1'
1*
#3780
0'
0*
#3790
1'
1*
#3800
0'
0*
#3810
1'
1*
#3820
0'
0*
#3830
b1 1
b100 5
1'
1*
1)
1,
#3840
0'
0*
#3850
b0 1
1'
1*
0)
0,
#3860
0'
0*
#3870
1'
1*
#3880
0'
0*
#3890
1'
1*
#3900
0'
0*
#3910
1'
1*
#3920
0'
0*
#3930
1'
1*
#3940
0'
0*
#3950
1'
1*
#3960
0'
0*
#3970
1'
1*
#3980
0'
0*
#3990
1'
1*
#4000
0'
0*
#4010
1'
1*
#4020
0'
0*
#4030
1'
1*
#4040
b1 1
0'
0*
1)
1,
#4050
14
1&
02
0$
03
0%
b1 -
b0 5
1'
1*
#4060
0'
0*
0)
0,
#4070
1'
1*
#4080
0'
0*
#4090
1'
1*
#4100
0'
0*
#4110
1'
1*
#4120
0'
0*
#4130
1'
1*
#4140
0'
0*
#4150
1'
1*
#4160
0'
0*
#4170
1'
1*
#4180
0'
0*
#4190
1'
1*
#4200
0'
0*
#4210
1'
1*
#4220
0'
0*
#4230
1'
1*
#4240
0'
0*
#4250
b10 1
b1 5
1'
1*
1)
1,
#4260
0'
0*
#4270
b1 1
1'
1*
0)
0,
#4280
0'
0*
#4290
1'
1*
#4300
0'
0*
#4310
1'
1*
#4320
0'
0*
#4330
1'
1*
#4340
0'
0*
#4350
1'
1*
#4360
0'
0*
#4370
1'
1*
#4380
0'
0*
#4390
1'
1*
#4400
0'
0*
#4410
1'
1*
#4420
0'
0*
#4430
1'
1*
#4440
0'
0*
#4450
1'
1*
#4460
b10 1
0'
0*
1)
1,
#4470
0/
0"
1.
1!
04
0&
13
1%
b0 5
b10 -
1'
1*
#4480
0'
0*
0)
0,
#4490
1'
1*
#4500
0'
0*
#4510
1'
1*
#4520
0'
0*
#4530
1'
1*
#4540
0'
0*
#4550
1'
1*
#4560
0'
0*
#4570
1'
1*
#4580
0'
0*
#4590
1'
1*
#4600
0'
0*
#4610
1'
1*
#4620
0'
0*
#4630
1'
1*
#4640
0'
0*
#4650
1'
1*
#4660
0'
0*
#4670
b1 5
1'
1*
1)
1,
#4680
0'
0*
#4690
1'
1*
0)
0,
#4700
0'
0*
#4710
1'
1*
#4720
0'
0*
#4730
1'
1*
#4740
0'
0*
#4750
1'
1*
#4760
0'
0*
#4770
1'
1*
#4780
0'
0*
#4790
1'
1*
#4800
0'
0*
#4810
1'
1*
#4820
0'
0*
#4830
1'
1*
#4840
0'
0*
#4850
1'
1*
#4860
0'
0*
#4870
1'
1*
#4880
0'
0*
1)
1,
#4890
b10 5
1'
1*
#4900
0'
0*
0)
0,
#4910
1'
1*
#4920
0'
0*
#4930
1'
1*
#4940
0'
0*
#4950
1'
1*
#4960
0'
0*
#4970
1'
1*
#4980
0'
0*
#4990
1'
1*
#5000
0'
0*
#5010
1'
1*
#5020
0'
0*
#5030
1'
1*
#5040
0'
0*
#5050
1'
1*
#5060
0'
0*
#5070
1'
1*
#5080
0'
0*
#5090
b11 5
1'
1*
1)
1,
#5100
0'
0*
#5110
1'
1*
0)
0,
#5120
0'
0*
#5130
1'
1*
#5140
0'
0*
#5150
1'
1*
#5160
0'
0*
#5170
1'
1*
#5180
0'
0*
#5190
1'
1*
#5200
0'
0*
#5210
1'
1*
#5220
0'
0*
#5230
1'
1*
#5240
0'
0*
#5250
1'
1*
#5260
0'
0*
#5270
1'
1*
#5280
0'
0*
#5290
1'
1*
#5300
0'
0*
1)
1,
#5310
b11 1
b100 5
1'
1*
#5320
b10 1
0'
0*
0)
0,
#5330
1'
1*
#5340
0'
0*
#5350
1'
1*
#5360
0'
0*
#5370
1'
1*
#5380
0'
0*
#5390
1'
1*
#5400
0'
0*
#5410
1'
1*
#5420
0'
0*
#5430
1'
1*
#5440
0'
0*
#5450
1'
1*
#5460
0'
0*
#5470
1'
1*
#5480
0'
0*
#5490
1'
1*
#5500
0'
0*
#5510
10
1#
0.
0!
0/
0"
b0 5
b11 -
b11 1
1'
1*
1)
1,
#5520
0'
0*
#5530
1'
1*
0)
0,
#5540
0'
0*
#5550
1'
1*
#5560
0'
0*
#5570
1'
1*
#5580
0'
0*
#5590
1'
1*
#5600
0'
0*
#5610
1'
1*
#5620
0'
0*
#5630
1'
1*
#5640
0'
0*
#5650
1'
1*
#5660
0'
0*
#5670
1'
1*
#5680
0'
0*
#5690
1'
1*
#5700
0'
0*
#5710
1'
1*
#5720
0'
0*
1)
1,
#5730
b0 1
b1 5
1'
1*
#5740
b11 1
0'
0*
0)
0,
#5750
1'
1*
#5760
0'
0*
#5770
1'
1*
#5780
0'
0*
#5790
1'
1*
#5800
0'
0*
#5810
1'
1*
#5820
0'
0*
#5830
1'
1*
#5840
0'
0*
#5850
1'
1*
#5860
0'
0*
#5870
1'
1*
#5880
0'
0*
#5890
1'
1*
#5900
0'
0*
#5910
1'
1*
#5920
0'
0*
#5930
03
0%
12
1$
00
0#
1/
1"
b0 -
b0 5
b0 1
1'
1*
1)
1,
#5940
0'
0*
#5950
1'
1*
0)
0,
#5960
0'
0*
#5970
1'
1*
#5980
0'
0*
#5990
1'
1*
#6000
0'
0*
#6010
1'
1*
#6020
0'
0*
#6030
1'
1*
#6040
0'
0*
#6050
1'
1*
#6060
0'
0*
#6070
1'
1*
#6080
0'
0*
#6090
1'
1*
#6100
0'
0*
#6110
1'
1*
#6120
0'
0*
#6130
1'
1*
#6140
0'
0*
1)
1,
#6150
b1 5
1'
1*
#6160
0'
0*
0)
0,
#6170
1'
1*
#6180
0'
0*
#6190
1'
1*
#6200
0'
0*
#6210
1'
1*
#6220
0'
0*
#6230
1'
1*
#6240
0'
0*
#6250
1'
1*
#6260
0'
0*
#6270
1'
1*
#6280
0'
0*
#6290
1'
1*
#6300
0'
0*
#6310
1'
1*
#6320
0'
0*
#6330
1'
1*
#6340
0'
0*
#6350
b10 5
1'
1*
1)
1,
#6360
0'
0*
#6370
1'
1*
0)
0,
