Lab2/problrm4_link/slave_fsm.v
// slave_fsm.v (fixed for broad Icarus compatibility)
// Latches data on req, asserts ack for 2 cycles minimum, then waits for req to drop before deasserting ack.
module slave_fsm (
    input  wire       clk,
    input  wire       rst,        // synchronous, active-high
    input  wire       req,        // from master
    input  wire [7:0] data_in,    // from master
    output reg        ack,        // to master
    output reg [7:0]  last_byte   // latched byte (observable from TB)
);
    // State encoding
    localparam [1:0] W_WAIT_REQ  = 2'd0,
                     W_ASSERT    = 2'd1, // assert ack and count 2 cycles
                     W_HOLD      = 2'd2, // after 2 cycles, keep ack until req==0
                     W_DROP      = 2'd3; // drop ack (1 cycle), then back to WAIT

    reg [1:0] state, nstate;
    reg [1:0] hold_cnt; // counts 0,1 for 2 cycles

    // Sequential
    always @(posedge clk) begin
        if (rst) begin
            state     <= W_WAIT_REQ;
            ack       <= 1'b0;
            last_byte <= 8'h00;
            hold_cnt  <= 2'd0;
        end else begin
            state <= nstate;

            case (state)
                W_WAIT_REQ: begin
                    ack <= 1'b0;
                    if (req) begin
                        // Latch byte on req (sample when req observed high)
                        last_byte <= data_in;
                        ack       <= 1'b1;
                        hold_cnt  <= 2'd0;
                    end
                end

                W_ASSERT: begin
                    // ack stays high and we count 2 cycles
                    ack <= 1'b1;
                    hold_cnt <= hold_cnt + 2'd1;
                end

                W_HOLD: begin
                    // After 2 cycles, keep ack high until req drops
                    ack <= 1'b1;
                end

                W_DROP: begin
                    // Drop ack for one cycle
                    ack <= 1'b0;
                end
            endcase
        end
    end

    // Next-state logic
    always @* begin
        nstate = state;
        case (state)
            W_WAIT_REQ: begin
                if (req) nstate = W_ASSERT;
            end
            W_ASSERT: begin
                if (hold_cnt == 2'd1) nstate = W_HOLD; // 2 cycles: 0 and 1
                else nstate = W_ASSERT;
            end
            W_HOLD: begin
                if (!req) nstate = W_DROP;
            end
            W_DROP: begin
                nstate = W_WAIT_REQ;
            end
            default: nstate = W_WAIT_REQ;
        endcase
    end
endmodule

Lab2/problrm4_link/master_fsm.v
// master_fsm.v (fixed for broad Icarus compatibility)
// Synchronous, active-high reset master for 4-phase req/ack handshake.
// Sends 4 bytes over an 8-bit data bus. Pulses 'done' for 1 cycle after final transfer.
module master_fsm (
    input  wire       clk,
    input  wire       rst,       // synchronous, active-high
    input  wire       ack,       // from slave
    output reg        req,       // to slave
    output reg [7:0]  data,      // to slave
    output reg        done       // 1-cycle pulse when burst completes
);
    // Parameters
    localparam integer N_BYTES = 4;

    // Simple pattern
    reg [7:0] rom [0:N_BYTES-1];
    initial begin
        rom[0] = 8'hA0;
        rom[1] = 8'hA1;
        rom[2] = 8'hA2;
        rom[3] = 8'hA3;
    end

    // Byte index
    reg [2:0] idx;

    // State encoding (avoid typedef enum for Icarus)
    localparam [2:0] S_IDLE     = 3'd0,
                     S_DRIVE    = 3'd1, // drive data + raise req
                     S_WAIT_ACK = 3'd2, // wait until ack==1
                     S_DROP_REQ = 3'd3, // drop req after ack seen
                     S_NEXT     = 3'd4, // advance index / decide next
                     S_DONE     = 3'd5; // pulse done

    reg [2:0] state, nstate;

    // Sequential
    always @(posedge clk) begin
        if (rst) begin
            state <= S_IDLE;
            req   <= 1'b0;
            data  <= 8'h00;
            done  <= 1'b0;
            idx   <= 3'd0;
        end else begin
            state <= nstate;
            // defaults that may be overridden in cases below
            done  <= 1'b0;
            case (state)
                S_IDLE: begin
                    idx  <= 3'd0;
                    req  <= 1'b0;
                    data <= 8'h00;
                end
                S_DRIVE: begin
                    data <= rom[idx];
                    req  <= 1'b1;
                end
                S_WAIT_ACK: begin
                    // hold req high, data valid
                    req  <= 1'b1;
                    data <= rom[idx];
                end
                S_DROP_REQ: begin
                    // drop req once ack observed
                    req  <= 1'b0;
                    data <= rom[idx];
                end
                S_NEXT: begin
                    // advance to next byte if any
                    if (idx < (N_BYTES-1)) begin
                        idx <= idx + 3'd1;
                    end
                end
                S_DONE: begin
                    req  <= 1'b0;
                    done <= 1'b1; // pulse for one cycle
                end
                default: ;
            endcase
        end
    end

    // Combinational next-state
    always @* begin
        nstate = state;
        case (state)
            S_IDLE:     nstate = S_DRIVE;
            S_DRIVE:    nstate = S_WAIT_ACK;
            S_WAIT_ACK: nstate = (ack ? S_DROP_REQ : S_WAIT_ACK);
            S_DROP_REQ: nstate = S_NEXT;
            S_NEXT:     nstate = (idx == (N_BYTES-1)) ? S_DONE : S_DRIVE;
            S_DONE:     nstate = S_DONE; // stay done; TB can reset to run again
            default:    nstate = S_IDLE;
        endcase
    end
endmodule

Lab2/problrm4_link/link_top.v
// link_top.v
// Connects master_fsm and slave_fsm together on a shared clk/rst.
module link_top (
    input  wire clk,
    input  wire rst,
    output wire done
);
    // Wires between master and slave
    wire        req_w;
    wire        ack_w;
    wire [7:0]  data_w;
    wire [7:0]  last_byte_w;

    master_fsm u_master (
        .clk (clk),
        .rst (rst),
        .ack (ack_w),
        .req (req_w),
        .data(data_w),
        .done(done)
    );

    slave_fsm u_slave (
        .clk      (clk),
        .rst      (rst),
        .req      (req_w),
        .data_in  (data_w),
        .ack      (ack_w),
        .last_byte(last_byte_w)
    );

    // Optional: expose some internal signals via hierarchical paths in TB.
endmodule

Lab2/problrm4_link/tb_link_top.v
// tb_link_top.v
`timescale 1ns/1ps

module tb_link_top;
    reg clk, rst;
    wire done;

    link_top dut (
        .clk (clk),
        .rst (rst),
        .done(done)
    );

    // Clock: 10ns period (100 MHz)
    initial clk = 1'b0;
    always #5 clk = ~clk;

    // Reset sequence
    initial begin
        rst = 1'b1;
        repeat (4) @(posedge clk);
        rst = 1'b0;
    end

    // VCD dumping
    initial begin
        $dumpfile("dump.vcd");
        $dumpvars(0, tb_link_top);
        // Dump useful internal signals
        $dumpvars(0, dut.u_master);
        $dumpvars(0, dut.u_slave);
    end

    // Monitors (hierarchical refs)
    wire        req   = dut.u_master.req;
    wire        ack   = dut.u_slave.ack;
    wire [7:0]  data  = dut.u_master.data;
    wire [7:0]  lastb = dut.u_slave.last_byte;

    // Simple scoreboard: collect 4 bytes and check values
    reg [7:0] got [0:3];
    integer i;
    initial begin
        for (i=0; i<4; i=i+1) got[i] = 8'h00;
    end

    // Capture on ack rising edge (first cycle of ack high)
    reg ack_d;
    always @(posedge clk) begin
        ack_d <= ack;
        if (!ack_d && ack) begin
            // count which byte this is
            integer idx;
            idx = (got[0]!=8'h00) + (got[1]!=8'h00) + (got[2]!=8'h00) + (got[3]!=8'h00);
            if (idx < 4) got[idx] <= lastb;
            $display("[%0t] ACK rise: data=%02h last_byte=%02h req=%0b", $time, data, lastb, req);
        end
    end

    // Stop when done observed
    always @(posedge clk) begin
        if (done) begin
            $display("[%0t] DONE observed.", $time);
            // Print summary
            $display("Received bytes: %02h %02h %02h %02h", got[0], got[1], got[2], got[3]);
            #20;
            $finish;
        end
    end

endmodule

Lab2/problrm4_link/dump.vcd
$date
	Fri Oct 03 12:22:31 2025
$end
$version
	Icarus Verilog
$end
$timescale
	1ps
$end
$scope module tb_link_top $end
$var wire 1 ! ack $end
$var wire 8 " data [7:0] $end
$var wire 8 # lastb [7:0] $end
$var wire 1 $ req $end
$var wire 1 % done $end
$var reg 1 & ack_d $end
$var reg 1 ' clk $end
$var reg 1 ( rst $end
$var integer 32 ) i [31:0] $end
$scope module dut $end
$var wire 1 ' clk $end
$var wire 1 ( rst $end
$var wire 1 * req_w $end
$var wire 8 + last_byte_w [7:0] $end
$var wire 1 % done $end
$var wire 8 , data_w [7:0] $end
$var wire 1 - ack_w $end
$scope module u_master $end
$var wire 1 ' clk $end
$var wire 1 ( rst $end
$var wire 1 - ack $end
$var parameter 32 . N_BYTES $end
$var parameter 3 / S_DONE $end
$var parameter 3 0 S_DRIVE $end
$var parameter 3 1 S_DROP_REQ $end
$var parameter 3 2 S_IDLE $end
$var parameter 3 3 S_NEXT $end
$var parameter 3 4 S_WAIT_ACK $end
$var reg 8 5 data [7:0] $end
$var reg 1 % done $end
$var reg 3 6 idx [2:0] $end
$var reg 3 7 nstate [2:0] $end
$var reg 1 * req $end
$var reg 3 8 state [2:0] $end
$upscope $end
$scope module u_slave $end
$var wire 1 ' clk $end
$var wire 8 9 data_in [7:0] $end
$var wire 1 * req $end
$var wire 1 ( rst $end
$var parameter 2 : W_ASSERT $end
$var parameter 2 ; W_DROP $end
$var parameter 2 < W_HOLD $end
$var parameter 2 = W_WAIT_REQ $end
$var reg 1 - ack $end
$var reg 2 > hold_cnt [1:0] $end
$var reg 8 ? last_byte [7:0] $end
$var reg 2 @ nstate [1:0] $end
$var reg 2 A state [1:0] $end
$upscope $end
$upscope $end
$scope begin $unm_blk_5 $end
$var integer 32 B idx [31:0] $end
$upscope $end
$upscope $end
$scope module tb_link_top $end
$scope module dut $end
$scope module u_master $end
$upscope $end
$upscope $end
$upscope $end
$scope module tb_link_top $end
$scope module dut $end
$scope module u_slave $end
$upscope $end
$upscope $end
$upscope $end
$enddefinitions $end
$comment Show the parameter values. $end
$dumpall
b0 =
b10 <
b11 ;
b1 :
b10 4
b100 3
b0 2
b11 1
b1 0
b101 /
b100 .
$end
#0
$dumpvars
bx B
bx A
bx @
bx ?
bx >
bx 9
bx 8
bx 7
bx 6
bx 5
x-
bx ,
bx +
x*
b100 )
1(
0'
x&
x%
x$
bx #
bx "
x!
$end
#5000
b1 7
b0 @
b0 6
0%
b0 "
b0 ,
b0 5
b0 9
0$
0*
b0 8
b0 >
b0 #
b0 +
b0 ?
0!
0-
b0 A
1'
#10000
0'
#15000
0&
1'
#20000
0'
#25000
1'
#30000
0'
#35000
0(
1'
#40000
0'
#45000
b10 7
b1 8
1'
#50000
0'
#55000
b1 @
1$
1*
b10100000 "
b10100000 ,
b10100000 5
b10100000 9
b10 8
1'
#60000
0'
#65000
b11 7
1!
1-
b10100000 #
b10100000 +
b10100000 ?
b1 A
1'
#70000
0'
#75000
b10 @
b100 7
1&
b1 >
b11 8
b0 B
1'
#80000
0'
#85000
b1 7
b11 @
0$
0*
b100 8
b10 >
b10 A
1'
#90000
0'
#95000
b0 @
b10 7
b11 A
b1 6
b1 8
1'
#100000
0'
#105000
b1 @
1$
1*
b10100001 "
b10100001 ,
b10100001 5
b10100001 9
b10 8
0!
0-
b0 A
1'
#110000
0'
#115000
b11 7
0&
b0 >
1!
1-
b10100001 #
b10100001 +
b10100001 ?
b1 A
1'
#120000
0'
#125000
b100 7
b10 @
b11 8
b1 >
1&
b1 B
1'
#130000
0'
#135000
b11 @
b1 7
b10 >
b10 A
0$
0*
b100 8
1'
#140000
0'
#145000
b10 7
b0 @
b10 6
b1 8
b11 A
1'
#150000
0'
#155000
b1 @
0!
0-
b0 A
1$
1*
b10100010 "
b10100010 ,
b10100010 5
b10100010 9
b10 8
1'
#160000
0'
#165000
b11 7
0&
b0 >
1!
1-
b10100010 #
b10100010 +
b10100010 ?
b1 A
1'
#170000
0'
#175000
b10 @
b100 7
b1 >
b11 8
1&
b10 B
1'
#180000
0'
#185000
b1 7
b11 @
0$
0*
b100 8
b10 >
b10 A
1'
#190000
0'
#195000
b0 @
b10 7
b11 A
b11 6
b1 8
1'
#200000
0'
#205000
b1 @
1$
1*
b10100011 "
b10100011 ,
b10100011 5
b10100011 9
b10 8
0!
0-
b0 A
1'
#210000
0'
#215000
b11 7
0&
b0 >
1!
1-
b10100011 #
b10100011 +
b10100011 ?
b1 A
1'
#220000
0'
#225000
b100 7
b10 @
b11 8
b1 >
1&
b11 B
1'
#230000
0'
#235000
b11 @
b101 7
b10 >
b10 A
0$
0*
b100 8
1'
#240000
0'
#245000
b0 @
b101 8
b11 A
1'
#250000
0'
#255000
0!
0-
b0 A
1%
1'
#260000
0'
#265000
0&
1%
1'
#270000
0'
#275000
1%
1'
#280000
0'
#285000
1%
1'
